todo_by/__init__.py
todo_by/main.py
todo_by/utils.py
todo_by-1.2.0.dist-info/METADATA
todo_by-1.2.0.dist-info/WHEEL
todo_by-1.2.0.dist-info/top_level.txt
todo_by-1.2.0.dist-info/RECORD
