Metadata-Version: 2.1
Name: todo-by
Version: 1.2.0
Summary: Runtime lifetimes for comments.
Home-page: https://github.com/barnumbirr/todo_by
Download-URL: https://github.com/barnumbirr/todo_by/archive/refs/heads/master.zip
Author: Martin Simon
Author-email: me@martinsimon.me
Classifier: Development Status :: 5 - Production/Stable
Classifier: Intended Audience :: Developers
Classifier: License :: OSI Approved :: MIT License
Classifier: Operating System :: OS Independent
Classifier: Programming Language :: Python :: 3
Classifier: Programming Language :: Python :: 3.8
Classifier: Programming Language :: Python :: 3.9
Classifier: Programming Language :: Python :: 3.10
